Metadata-Version: 2.1
Name: online-store-made-for-uni
Version: 0.1.0
Summary: Исполняемый пакет для управления пользователями и заказами в онлайн-магазине
Author-email: Lopss <pechenkov172@gmail.com>
License: MIT
Requires-Python: >=3.8
Requires-Dist: requests>=2.25.1
Requires-Dist: numpy>=1.19.2
